[
  {
    "url": "https://api.github.com/repos/apache/spark/issues/comments/1469541110",
    "html_url": "https://github.com/apache/spark/pull/40410#issuecomment-1469541110",
    "issue_url": "https://api.github.com/repos/apache/spark/issues/40410",
    "id": 1469541110,
    "node_id": "IC_kwDOAQXtWs5Xl2r2",
    "user": {
      "login": "beliefer",
      "id": 8486025,
      "node_id": "MDQ6VXNlcjg0ODYwMjU=",
      "avatar_url": "https://avatars.githubusercontent.com/u/8486025?v=4",
      "gravatar_id": "",
      "url": "https://api.github.com/users/beliefer",
      "html_url": "https://github.com/beliefer",
      "followers_url": "https://api.github.com/users/beliefer/followers",
      "following_url": "https://api.github.com/users/beliefer/following{/other_user}",
      "gists_url": "https://api.github.com/users/beliefer/gists{/gist_id}",
      "starred_url": "https://api.github.com/users/beliefer/starred{/owner}{/repo}",
      "subscriptions_url": "https://api.github.com/users/beliefer/subscriptions",
      "organizations_url": "https://api.github.com/users/beliefer/orgs",
      "repos_url": "https://api.github.com/users/beliefer/repos",
      "events_url": "https://api.github.com/users/beliefer/events{/privacy}",
      "received_events_url": "https://api.github.com/users/beliefer/received_events",
      "type": "User",
      "site_admin": false
    },
    "created_at": "2023-03-15T08:13:07Z",
    "updated_at": "2023-03-15T08:13:07Z",
    "author_association": "CONTRIBUTOR",
    "body": "ping @cloud-fan cc @zhengruifeng ",
    "reactions": {
      "url": "https://api.github.com/repos/apache/spark/issues/comments/1469541110/reactions",
      "total_count": 0,
      "+1": 0,
      "-1": 0,
      "laugh": 0,
      "hooray": 0,
      "confused": 0,
      "heart": 0,
      "rocket": 0,
      "eyes": 0
    },
    "performed_via_github_app": null
  },
  {
    "url": "https://api.github.com/repos/apache/spark/issues/comments/1469878236",
    "html_url": "https://github.com/apache/spark/pull/40410#issuecomment-1469878236",
    "issue_url": "https://api.github.com/repos/apache/spark/issues/40410",
    "id": 1469878236,
    "node_id": "IC_kwDOAQXtWs5XnI_c",
    "user": {
      "login": "cloud-fan",
      "id": 3182036,
      "node_id": "MDQ6VXNlcjMxODIwMzY=",
      "avatar_url": "https://avatars.githubusercontent.com/u/3182036?v=4",
      "gravatar_id": "",
      "url": "https://api.github.com/users/cloud-fan",
      "html_url": "https://github.com/cloud-fan",
      "followers_url": "https://api.github.com/users/cloud-fan/followers",
      "following_url": "https://api.github.com/users/cloud-fan/following{/other_user}",
      "gists_url": "https://api.github.com/users/cloud-fan/gists{/gist_id}",
      "starred_url": "https://api.github.com/users/cloud-fan/starred{/owner}{/repo}",
      "subscriptions_url": "https://api.github.com/users/cloud-fan/subscriptions",
      "organizations_url": "https://api.github.com/users/cloud-fan/orgs",
      "repos_url": "https://api.github.com/users/cloud-fan/repos",
      "events_url": "https://api.github.com/users/cloud-fan/events{/privacy}",
      "received_events_url": "https://api.github.com/users/cloud-fan/received_events",
      "type": "User",
      "site_admin": false
    },
    "created_at": "2023-03-15T12:01:34Z",
    "updated_at": "2023-03-15T12:01:34Z",
    "author_association": "CONTRIBUTOR",
    "body": "thanks, merging to master!",
    "reactions": {
      "url": "https://api.github.com/repos/apache/spark/issues/comments/1469878236/reactions",
      "total_count": 1,
      "+1": 1,
      "-1": 0,
      "laugh": 0,
      "hooray": 0,
      "confused": 0,
      "heart": 0,
      "rocket": 0,
      "eyes": 0
    },
    "performed_via_github_app": null
  },
  {
    "url": "https://api.github.com/repos/apache/spark/issues/comments/1469932642",
    "html_url": "https://github.com/apache/spark/pull/40410#issuecomment-1469932642",
    "issue_url": "https://api.github.com/repos/apache/spark/issues/40410",
    "id": 1469932642,
    "node_id": "IC_kwDOAQXtWs5XnWRi",
    "user": {
      "login": "beliefer",
      "id": 8486025,
      "node_id": "MDQ6VXNlcjg0ODYwMjU=",
      "avatar_url": "https://avatars.githubusercontent.com/u/8486025?v=4",
      "gravatar_id": "",
      "url": "https://api.github.com/users/beliefer",
      "html_url": "https://github.com/beliefer",
      "followers_url": "https://api.github.com/users/beliefer/followers",
      "following_url": "https://api.github.com/users/beliefer/following{/other_user}",
      "gists_url": "https://api.github.com/users/beliefer/gists{/gist_id}",
      "starred_url": "https://api.github.com/users/beliefer/starred{/owner}{/repo}",
      "subscriptions_url": "https://api.github.com/users/beliefer/subscriptions",
      "organizations_url": "https://api.github.com/users/beliefer/orgs",
      "repos_url": "https://api.github.com/users/beliefer/repos",
      "events_url": "https://api.github.com/users/beliefer/events{/privacy}",
      "received_events_url": "https://api.github.com/users/beliefer/received_events",
      "type": "User",
      "site_admin": false
    },
    "created_at": "2023-03-15T12:40:40Z",
    "updated_at": "2023-03-15T12:40:40Z",
    "author_association": "CONTRIBUTOR",
    "body": "@cloud-fan @dongjoon-hyun Thank you !",
    "reactions": {
      "url": "https://api.github.com/repos/apache/spark/issues/comments/1469932642/reactions",
      "total_count": 1,
      "+1": 1,
      "-1": 0,
      "laugh": 0,
      "hooray": 0,
      "confused": 0,
      "heart": 0,
      "rocket": 0,
      "eyes": 0
    },
    "performed_via_github_app": null
  },
  {
    "url": "https://api.github.com/repos/apache/spark/issues/comments/1470311818",
    "html_url": "https://github.com/apache/spark/pull/40410#issuecomment-1470311818",
    "issue_url": "https://api.github.com/repos/apache/spark/issues/40410",
    "id": 1470311818,
    "node_id": "IC_kwDOAQXtWs5Xoy2K",
    "user": {
      "login": "dongjoon-hyun",
      "id": 9700541,
      "node_id": "MDQ6VXNlcjk3MDA1NDE=",
      "avatar_url": "https://avatars.githubusercontent.com/u/9700541?v=4",
      "gravatar_id": "",
      "url": "https://api.github.com/users/dongjoon-hyun",
      "html_url": "https://github.com/dongjoon-hyun",
      "followers_url": "https://api.github.com/users/dongjoon-hyun/followers",
      "following_url": "https://api.github.com/users/dongjoon-hyun/following{/other_user}",
      "gists_url": "https://api.github.com/users/dongjoon-hyun/gists{/gist_id}",
      "starred_url": "https://api.github.com/users/dongjoon-hyun/starred{/owner}{/repo}",
      "subscriptions_url": "https://api.github.com/users/dongjoon-hyun/subscriptions",
      "organizations_url": "https://api.github.com/users/dongjoon-hyun/orgs",
      "repos_url": "https://api.github.com/users/dongjoon-hyun/repos",
      "events_url": "https://api.github.com/users/dongjoon-hyun/events{/privacy}",
      "received_events_url": "https://api.github.com/users/dongjoon-hyun/received_events",
      "type": "User",
      "site_admin": false
    },
    "created_at": "2023-03-15T16:02:21Z",
    "updated_at": "2023-03-15T16:02:21Z",
    "author_association": "MEMBER",
    "body": "Thank you, @beliefer and @cloud-fan .",
    "reactions": {
      "url": "https://api.github.com/repos/apache/spark/issues/comments/1470311818/reactions",
      "total_count": 0,
      "+1": 0,
      "-1": 0,
      "laugh": 0,
      "hooray": 0,
      "confused": 0,
      "heart": 0,
      "rocket": 0,
      "eyes": 0
    },
    "performed_via_github_app": null
  }
]
