[
  {
    "url": "https://api.github.com/repos/apache/spark/issues/comments/1499909905",
    "html_url": "https://github.com/apache/spark/pull/40696#issuecomment-1499909905",
    "issue_url": "https://api.github.com/repos/apache/spark/issues/40696",
    "id": 1499909905,
    "node_id": "IC_kwDOAQXtWs5ZZs8R",
    "user": {
      "login": "anishshri-db",
      "id": 100322362,
      "node_id": "U_kgDOBfrMOg",
      "avatar_url": "https://avatars.githubusercontent.com/u/100322362?v=4",
      "gravatar_id": "",
      "url": "https://api.github.com/users/anishshri-db",
      "html_url": "https://github.com/anishshri-db",
      "followers_url": "https://api.github.com/users/anishshri-db/followers",
      "following_url": "https://api.github.com/users/anishshri-db/following{/other_user}",
      "gists_url": "https://api.github.com/users/anishshri-db/gists{/gist_id}",
      "starred_url": "https://api.github.com/users/anishshri-db/starred{/owner}{/repo}",
      "subscriptions_url": "https://api.github.com/users/anishshri-db/subscriptions",
      "organizations_url": "https://api.github.com/users/anishshri-db/orgs",
      "repos_url": "https://api.github.com/users/anishshri-db/repos",
      "events_url": "https://api.github.com/users/anishshri-db/events{/privacy}",
      "received_events_url": "https://api.github.com/users/anishshri-db/received_events",
      "type": "User",
      "site_admin": false
    },
    "created_at": "2023-04-07T04:05:13Z",
    "updated_at": "2023-04-07T04:05:13Z",
    "author_association": "CONTRIBUTOR",
    "body": "@HeartSaVioR - PTAL. Thanks",
    "reactions": {
      "url": "https://api.github.com/repos/apache/spark/issues/comments/1499909905/reactions",
      "total_count": 0,
      "+1": 0,
      "-1": 0,
      "laugh": 0,
      "hooray": 0,
      "confused": 0,
      "heart": 0,
      "rocket": 0,
      "eyes": 0
    },
    "performed_via_github_app": null
  },
  {
    "url": "https://api.github.com/repos/apache/spark/issues/comments/1499982120",
    "html_url": "https://github.com/apache/spark/pull/40696#issuecomment-1499982120",
    "issue_url": "https://api.github.com/repos/apache/spark/issues/40696",
    "id": 1499982120,
    "node_id": "IC_kwDOAQXtWs5ZZ-ko",
    "user": {
      "login": "HeartSaVioR",
      "id": 1317309,
      "node_id": "MDQ6VXNlcjEzMTczMDk=",
      "avatar_url": "https://avatars.githubusercontent.com/u/1317309?v=4",
      "gravatar_id": "",
      "url": "https://api.github.com/users/HeartSaVioR",
      "html_url": "https://github.com/HeartSaVioR",
      "followers_url": "https://api.github.com/users/HeartSaVioR/followers",
      "following_url": "https://api.github.com/users/HeartSaVioR/following{/other_user}",
      "gists_url": "https://api.github.com/users/HeartSaVioR/gists{/gist_id}",
      "starred_url": "https://api.github.com/users/HeartSaVioR/starred{/owner}{/repo}",
      "subscriptions_url": "https://api.github.com/users/HeartSaVioR/subscriptions",
      "organizations_url": "https://api.github.com/users/HeartSaVioR/orgs",
      "repos_url": "https://api.github.com/users/HeartSaVioR/repos",
      "events_url": "https://api.github.com/users/HeartSaVioR/events{/privacy}",
      "received_events_url": "https://api.github.com/users/HeartSaVioR/received_events",
      "type": "User",
      "site_admin": false
    },
    "created_at": "2023-04-07T06:24:16Z",
    "updated_at": "2023-04-07T06:24:16Z",
    "author_association": "CONTRIBUTOR",
    "body": "CI fails with odd errors.\r\n@anishshri-db Could you please rebase so that CI is retriggered? If the new trial fails again, maybe good to post to dev@ and see whether someone encountered this before, and/or someone is willing to volunteer to fix if that's not a transient issue.",
    "reactions": {
      "url": "https://api.github.com/repos/apache/spark/issues/comments/1499982120/reactions",
      "total_count": 0,
      "+1": 0,
      "-1": 0,
      "laugh": 0,
      "hooray": 0,
      "confused": 0,
      "heart": 0,
      "rocket": 0,
      "eyes": 0
    },
    "performed_via_github_app": null
  },
  {
    "url": "https://api.github.com/repos/apache/spark/issues/comments/1500446559",
    "html_url": "https://github.com/apache/spark/pull/40696#issuecomment-1500446559",
    "issue_url": "https://api.github.com/repos/apache/spark/issues/40696",
    "id": 1500446559,
    "node_id": "IC_kwDOAQXtWs5Zbv9f",
    "user": {
      "login": "anishshri-db",
      "id": 100322362,
      "node_id": "U_kgDOBfrMOg",
      "avatar_url": "https://avatars.githubusercontent.com/u/100322362?v=4",
      "gravatar_id": "",
      "url": "https://api.github.com/users/anishshri-db",
      "html_url": "https://github.com/anishshri-db",
      "followers_url": "https://api.github.com/users/anishshri-db/followers",
      "following_url": "https://api.github.com/users/anishshri-db/following{/other_user}",
      "gists_url": "https://api.github.com/users/anishshri-db/gists{/gist_id}",
      "starred_url": "https://api.github.com/users/anishshri-db/starred{/owner}{/repo}",
      "subscriptions_url": "https://api.github.com/users/anishshri-db/subscriptions",
      "organizations_url": "https://api.github.com/users/anishshri-db/orgs",
      "repos_url": "https://api.github.com/users/anishshri-db/repos",
      "events_url": "https://api.github.com/users/anishshri-db/events{/privacy}",
      "received_events_url": "https://api.github.com/users/anishshri-db/received_events",
      "type": "User",
      "site_admin": false
    },
    "created_at": "2023-04-07T16:36:56Z",
    "updated_at": "2023-04-07T16:36:56Z",
    "author_association": "CONTRIBUTOR",
    "body": ">  Could you please rebase so that CI is retriggered? If the new trial fails again, maybe good to post to dev@ and see whether someone encountered this before, and/or someone is willing to volunteer to fix if that's not a transient issue.\r\n\r\nSeems like a known issue someone already posted to dev channel - https://github.com/sbt/sbt/issues/7202",
    "reactions": {
      "url": "https://api.github.com/repos/apache/spark/issues/comments/1500446559/reactions",
      "total_count": 0,
      "+1": 0,
      "-1": 0,
      "laugh": 0,
      "hooray": 0,
      "confused": 0,
      "heart": 0,
      "rocket": 0,
      "eyes": 0
    },
    "performed_via_github_app": null
  },
  {
    "url": "https://api.github.com/repos/apache/spark/issues/comments/1500555522",
    "html_url": "https://github.com/apache/spark/pull/40696#issuecomment-1500555522",
    "issue_url": "https://api.github.com/repos/apache/spark/issues/40696",
    "id": 1500555522,
    "node_id": "IC_kwDOAQXtWs5ZcKkC",
    "user": {
      "login": "anishshri-db",
      "id": 100322362,
      "node_id": "U_kgDOBfrMOg",
      "avatar_url": "https://avatars.githubusercontent.com/u/100322362?v=4",
      "gravatar_id": "",
      "url": "https://api.github.com/users/anishshri-db",
      "html_url": "https://github.com/anishshri-db",
      "followers_url": "https://api.github.com/users/anishshri-db/followers",
      "following_url": "https://api.github.com/users/anishshri-db/following{/other_user}",
      "gists_url": "https://api.github.com/users/anishshri-db/gists{/gist_id}",
      "starred_url": "https://api.github.com/users/anishshri-db/starred{/owner}{/repo}",
      "subscriptions_url": "https://api.github.com/users/anishshri-db/subscriptions",
      "organizations_url": "https://api.github.com/users/anishshri-db/orgs",
      "repos_url": "https://api.github.com/users/anishshri-db/repos",
      "events_url": "https://api.github.com/users/anishshri-db/events{/privacy}",
      "received_events_url": "https://api.github.com/users/anishshri-db/received_events",
      "type": "User",
      "site_admin": false
    },
    "created_at": "2023-04-07T19:03:19Z",
    "updated_at": "2023-04-07T19:03:19Z",
    "author_association": "CONTRIBUTOR",
    "body": "@HeartSaVioR - all tests passed. Please merge when you get a chance. Thx",
    "reactions": {
      "url": "https://api.github.com/repos/apache/spark/issues/comments/1500555522/reactions",
      "total_count": 0,
      "+1": 0,
      "-1": 0,
      "laugh": 0,
      "hooray": 0,
      "confused": 0,
      "heart": 0,
      "rocket": 0,
      "eyes": 0
    },
    "performed_via_github_app": null
  },
  {
    "url": "https://api.github.com/repos/apache/spark/issues/comments/1501422540",
    "html_url": "https://github.com/apache/spark/pull/40696#issuecomment-1501422540",
    "issue_url": "https://api.github.com/repos/apache/spark/issues/40696",
    "id": 1501422540,
    "node_id": "IC_kwDOAQXtWs5ZfePM",
    "user": {
      "login": "HeartSaVioR",
      "id": 1317309,
      "node_id": "MDQ6VXNlcjEzMTczMDk=",
      "avatar_url": "https://avatars.githubusercontent.com/u/1317309?v=4",
      "gravatar_id": "",
      "url": "https://api.github.com/users/HeartSaVioR",
      "html_url": "https://github.com/HeartSaVioR",
      "followers_url": "https://api.github.com/users/HeartSaVioR/followers",
      "following_url": "https://api.github.com/users/HeartSaVioR/following{/other_user}",
      "gists_url": "https://api.github.com/users/HeartSaVioR/gists{/gist_id}",
      "starred_url": "https://api.github.com/users/HeartSaVioR/starred{/owner}{/repo}",
      "subscriptions_url": "https://api.github.com/users/HeartSaVioR/subscriptions",
      "organizations_url": "https://api.github.com/users/HeartSaVioR/orgs",
      "repos_url": "https://api.github.com/users/HeartSaVioR/repos",
      "events_url": "https://api.github.com/users/HeartSaVioR/events{/privacy}",
      "received_events_url": "https://api.github.com/users/HeartSaVioR/received_events",
      "type": "User",
      "site_admin": false
    },
    "created_at": "2023-04-10T05:46:41Z",
    "updated_at": "2023-04-10T05:46:41Z",
    "author_association": "CONTRIBUTOR",
    "body": "Missed the notification. Thanks! Merging to master.",
    "reactions": {
      "url": "https://api.github.com/repos/apache/spark/issues/comments/1501422540/reactions",
      "total_count": 0,
      "+1": 0,
      "-1": 0,
      "laugh": 0,
      "hooray": 0,
      "confused": 0,
      "heart": 0,
      "rocket": 0,
      "eyes": 0
    },
    "performed_via_github_app": null
  }
]
