{
  "url": "https://api.github.com/repos/apache/spark/issues/40396",
  "repository_url": "https://api.github.com/repos/apache/spark",
  "labels_url": "https://api.github.com/repos/apache/spark/issues/40396/labels{/name}",
  "comments_url": "https://api.github.com/repos/apache/spark/issues/40396/comments",
  "events_url": "https://api.github.com/repos/apache/spark/issues/40396/events",
  "html_url": "https://github.com/apache/spark/pull/40396",
  "id": 1621243309,
  "node_id": "PR_kwDOAQXtWs5L4ZM-",
  "number": 40396,
  "title": "[SPARK-42772][SQL] Change the default value of JDBC options about push down to true",
  "user": {
    "login": "beliefer",
    "id": 8486025,
    "node_id": "MDQ6VXNlcjg0ODYwMjU=",
    "avatar_url": "https://avatars.githubusercontent.com/u/8486025?v=4",
    "gravatar_id": "",
    "url": "https://api.github.com/users/beliefer",
    "html_url": "https://github.com/beliefer",
    "followers_url": "https://api.github.com/users/beliefer/followers",
    "following_url": "https://api.github.com/users/beliefer/following{/other_user}",
    "gists_url": "https://api.github.com/users/beliefer/gists{/gist_id}",
    "starred_url": "https://api.github.com/users/beliefer/starred{/owner}{/repo}",
    "subscriptions_url": "https://api.github.com/users/beliefer/subscriptions",
    "organizations_url": "https://api.github.com/users/beliefer/orgs",
    "repos_url": "https://api.github.com/users/beliefer/repos",
    "events_url": "https://api.github.com/users/beliefer/events{/privacy}",
    "received_events_url": "https://api.github.com/users/beliefer/received_events",
    "type": "User",
    "site_admin": false
  },
  "labels": [
    {
      "id": 1405794576,
      "node_id": "MDU6TGFiZWwxNDA1Nzk0NTc2",
      "url": "https://api.github.com/repos/apache/spark/labels/SQL",
      "name": "SQL",
      "color": "ededed",
      "default": false,
      "description": null
    },
    {
      "id": 1981471081,
      "node_id": "MDU6TGFiZWwxOTgxNDcxMDgx",
      "url": "https://api.github.com/repos/apache/spark/labels/DOCS",
      "name": "DOCS",
      "color": "ededed",
      "default": false,
      "description": null
    }
  ],
  "state": "closed",
  "locked": false,
  "assignee": null,
  "assignees": [

  ],
  "milestone": null,
  "comments": 5,
  "created_at": "2023-03-13T10:57:11Z",
  "updated_at": "2023-03-16T03:16:42Z",
  "closed_at": "2023-03-16T01:04:23Z",
  "author_association": "CONTRIBUTOR",
  "active_lock_reason": null,
  "draft": false,
  "pull_request": {
    "url": "https://api.github.com/repos/apache/spark/pulls/40396",
    "html_url": "https://github.com/apache/spark/pull/40396",
    "diff_url": "https://github.com/apache/spark/pull/40396.diff",
    "patch_url": "https://github.com/apache/spark/pull/40396.patch",
    "merged_at": null
  },
  "body": "### What changes were proposed in this pull request?\r\nCurrently, DS V2 pushdown could let JDBC dialect decide to push down `OFFSET`, `LIMIT` and table sample. Because some databases doesn't support one of them, so we should change the default value of these pushdown API false. If one database support the syntax, the JDBC dialect should overwrite the value.\r\n\r\nWe also have a lot of JDBC options about push down, such as `pushDownOffset`. Users could change the option value to allow or disallow push down.\r\n\r\n### Why are the changes needed?\r\nThis PR change all JDBC v2 pushdown options to true and change all the dialect's pushdown API to false.\r\n\r\n\r\n### Does this PR introduce _any_ user-facing change?\r\n'Yes'.\r\nThe default behavior of pushdown framework is not push down SQL syntax to JDBC data source.\r\nUsers could control the pushdown enable or disable with JDBC options about push down, such as `pushDownOffset`. \r\n\r\n\r\n### How was this patch tested?\r\nTest cases updated.\r\n",
  "closed_by": {
    "login": "cloud-fan",
    "id": 3182036,
    "node_id": "MDQ6VXNlcjMxODIwMzY=",
    "avatar_url": "https://avatars.githubusercontent.com/u/3182036?v=4",
    "gravatar_id": "",
    "url": "https://api.github.com/users/cloud-fan",
    "html_url": "https://github.com/cloud-fan",
    "followers_url": "https://api.github.com/users/cloud-fan/followers",
    "following_url": "https://api.github.com/users/cloud-fan/following{/other_user}",
    "gists_url": "https://api.github.com/users/cloud-fan/gists{/gist_id}",
    "starred_url": "https://api.github.com/users/cloud-fan/starred{/owner}{/repo}",
    "subscriptions_url": "https://api.github.com/users/cloud-fan/subscriptions",
    "organizations_url": "https://api.github.com/users/cloud-fan/orgs",
    "repos_url": "https://api.github.com/users/cloud-fan/repos",
    "events_url": "https://api.github.com/users/cloud-fan/events{/privacy}",
    "received_events_url": "https://api.github.com/users/cloud-fan/received_events",
    "type": "User",
    "site_admin": false
  },
  "reactions": {
    "url": "https://api.github.com/repos/apache/spark/issues/40396/reactions",
    "total_count": 0,
    "+1": 0,
    "-1": 0,
    "laugh": 0,
    "hooray": 0,
    "confused": 0,
    "heart": 0,
    "rocket": 0,
    "eyes": 0
  },
  "timeline_url": "https://api.github.com/repos/apache/spark/issues/40396/timeline",
  "performed_via_github_app": null,
  "state_reason": null
}
